tests/__init__.py
tests/context.py
tests/test_advanced.py
tests/test_basic.py
ukbiobank/__init__.py
ukbiobank/ukbio.py
ukbiobank/data_coding/Data_Dictionary_Showcase.csv
ukbiobank/data_coding/coding19.tsv
ukbiobank/data_coding/coding6.tsv
ukbiobank/data_coding/coding87.tsv
ukbiobank/filtering/__init__.py
ukbiobank/filtering/filtering.py
ukbiobank/filtering/illness.py
ukbiobank/gui/__init__.py
ukbiobank/gui/load_frame.py
ukbiobank/gui/menu_frame.py
ukbiobank/gui/output_csv.py
ukbiobank/gui/select_illness.py
ukbiobank/gui/select_variables.py
ukbiobank/gui/ukbio_gui.py
ukbiobank/utils/__init__.py
ukbiobank/utils/utils.py
ukbiobank_tools-1.0.5.dist-info/LICENSE
ukbiobank_tools-1.0.5.dist-info/METADATA
ukbiobank_tools-1.0.5.dist-info/WHEEL
ukbiobank_tools-1.0.5.dist-info/top_level.txt
ukbiobank_tools-1.0.5.dist-info/RECORD
