Metadata-Version: 2.1
Name: ukbiobank-tools
Version: 1.0.5
Summary: Useful tools for working with UK Biobank meta-data
Home-page: https://github.com/jnecus/ukbiobank-tools
Author: Joe Necus
Author-email: joenecus@gmail.com
License: Copyright (c) 2020, Joe Necus
Requires-Dist: pandas
Provides-Extra: docs
Requires-Dist: sphinx ; extra == 'docs'
Requires-Dist: sphinxcontrib-httpdomain ; extra == 'docs'
Requires-Dist: sphinx-rtd-theme ; extra == 'docs'
